embedding_suite/__init__.py
embedding_suite/client.py
embedding_suite/provider.py
embedding_suite/providers/cohere_provider.py
embedding_suite/providers/huggingface_provider.py
embedding_suite/providers/mistral_provider.py
embedding_suite/providers/openai_provider.py
embedding_suite/providers/sentencetransformers_provider.py
embedding_suite/providers/voyageai_provider.py
embedding_suite/utils/config.py
embedding_suite-0.1.7.dist-info/METADATA
embedding_suite-0.1.7.dist-info/WHEEL
embedding_suite-0.1.7.dist-info/top_level.txt
embedding_suite-0.1.7.dist-info/RECORD
