Metadata-Version: 2.2
Name: embedding-suite
Version: 0.1.7
Summary: A simple, unified interface for generating embeddings from various providers.
License: MIT
Requires-Python: >=3.10
Requires-Dist: python-dotenv>=1.0.1
Requires-Dist: requests>=2.32.3
